        {
                "Student" : [

                    {
                        "CompanyName" : "Facebook",
                        "Company_age" : 25
                    },
                
                    {
                        "CompanyName": "Google",
                        "Company_age" : 34
                    },
                
                    {
                        "CompanyName" : "Apple",
                        "Company_age" : 56 
                
                    }
                ]
        
        
        }
